magic 03f30d0a
<code>
   <argcount> 0 </argcount>
   <nlocals> 0</nlocals>
   <stacksize> 11</stacksize>
   <flags> 0040</flags>
   <code>
      6400006401008401005a00006402005a0100650000640300640000640400
      640500640600640700640800640000640900640400830602014865000064
      03006400008302000148650000640300640000640a006404008302010164
      0b008400005a02004865020064030064000083020001640c008400005a03
      004865030064030083010001640d008400005a0400640e008400005a0500
      640f0053
   </code>
   <dis>
  1           0 LOAD_CONST               0 (2)
              3 LOAD_CONST               1 (<code object foo at 0x7f0e4bdbddb0, file "test_func_param2.py", line 1>)
              6 MAKE_FUNCTION            1
              9 STORE_NAME               0 (foo)

 14          12 LOAD_CONST               2 (10)
             15 STORE_NAME               1 (t)

 15          18 LOAD_NAME                0 (foo)
             21 LOAD_CONST               3 (1)
             24 LOAD_CONST               0 (2)
             27 LOAD_CONST               4 (3)
             30 LOAD_CONST               5 (4)
             33 LOAD_CONST               6 (5)
             36 LOAD_CONST               7 (6)
             39 LOAD_CONST               8 ('b')
             42 LOAD_CONST               0 (2)
             45 LOAD_CONST               9 ('c')
             48 LOAD_CONST               4 (3)
             51 CALL_FUNCTION          518
             54 POP_TOP             

 17          55 PRINT_NEWLINE       

 18          56 LOAD_NAME                0 (foo)
             59 LOAD_CONST               3 (1)
             62 LOAD_CONST               0 (2)
             65 CALL_FUNCTION            2
             68 POP_TOP             

 20          69 PRINT_NEWLINE       

 21          70 LOAD_NAME                0 (foo)
             73 LOAD_CONST               3 (1)
             76 LOAD_CONST               0 (2)
             79 LOAD_CONST              10 ('n')
             82 LOAD_CONST               4 (3)
             85 CALL_FUNCTION          258
             88 POP_TOP             

 23          89 LOAD_CONST              11 (<code object foo2 at 0x7f0e4bdbdeb0, file "test_func_param2.py", line 23>)
             92 MAKE_FUNCTION            0
             95 STORE_NAME               2 (foo2)

 27          98 PRINT_NEWLINE       

 28          99 LOAD_NAME                2 (foo2)
            102 LOAD_CONST               3 (1)
            105 LOAD_CONST               0 (2)
            108 CALL_FUNCTION            2
            111 POP_TOP             

 30         112 LOAD_CONST              12 (<code object foo3 at 0x7f0e4bdbdf30, file "test_func_param2.py", line 30>)
            115 MAKE_FUNCTION            0
            118 STORE_NAME               3 (foo3)

 33         121 PRINT_NEWLINE       

 34         122 LOAD_NAME                3 (foo3)
            125 LOAD_CONST               3 (1)
            128 CALL_FUNCTION            1
            131 POP_TOP             

 36         132 LOAD_CONST              13 (<code object foo4 at 0x7f0e4bdd11b0, file "test_func_param2.py", line 36>)
            135 MAKE_FUNCTION            0
            138 STORE_NAME               4 (foo4)

 39         141 LOAD_CONST              14 (<code object foo5 at 0x7f0e4bdd1030, file "test_func_param2.py", line 39>)
            144 MAKE_FUNCTION            0
            147 STORE_NAME               5 (foo5)
            150 LOAD_CONST              15 (None)
            153 RETURN_VALUE        
   </dis>
   <names> ('foo', 't', 'foo2', 'foo3', 'foo4', 'foo5')</names>
   <varnames> ()</varnames>
   <freevars> ()</freevars>
   <cellvars> ()</cellvars>
   <filename> 'test_func_param2.py'</filename>
   <name> '<module>'</name>
   <firstlineno> 1</firstlineno>
   <consts>
      2
      <code>
         <argcount> 3 </argcount>
         <nlocals> 9</nlocals>
         <stacksize> 3</stacksize>
         <flags> 004f</flags>
         <code>
            6401007d05007c000047487c010047487c0200474864020047487813007c
            0300445d0b007d06007c060047487121005764030047487823007c04006a
            0000830000445d15005c02007d07007d08007c0700477c08004748714200
            57640400474864000053
         </code>
         <dis>
  2           0 LOAD_CONST               1 (5)
              3 STORE_FAST               5 (x)

  3           6 LOAD_FAST                0 (a)
              9 PRINT_ITEM          
             10 PRINT_NEWLINE       

  4          11 LOAD_FAST                1 (m)
             14 PRINT_ITEM          
             15 PRINT_NEWLINE       

  5          16 LOAD_FAST                2 (n)
             19 PRINT_ITEM          
             20 PRINT_NEWLINE       

  6          21 LOAD_CONST               2 ('args:')
             24 PRINT_ITEM          
             25 PRINT_NEWLINE       

  7          26 SETUP_LOOP              19 (to 48)
             29 LOAD_FAST                3 (args)
             32 GET_ITER            
        >>   33 FOR_ITER                11 (to 47)
             36 STORE_FAST               6 (p)

  8          39 LOAD_FAST                6 (p)
             42 PRINT_ITEM          
             43 PRINT_NEWLINE       
             44 JUMP_ABSOLUTE           33
        >>   47 POP_BLOCK           

  9     >>   48 LOAD_CONST               3 ('kwargs:')
             51 PRINT_ITEM          
             52 PRINT_NEWLINE       

 10          53 SETUP_LOOP              35 (to 91)
             56 LOAD_FAST                4 (kwargs)
             59 LOAD_ATTR                0 (items)
             62 CALL_FUNCTION            0
             65 GET_ITER            
        >>   66 FOR_ITER                21 (to 90)
             69 UNPACK_SEQUENCE          2
             72 STORE_FAST               7 (k)
             75 STORE_FAST               8 (v)

 11          78 LOAD_FAST                7 (k)
             81 PRINT_ITEM          
             82 LOAD_FAST                8 (v)
             85 PRINT_ITEM          
             86 PRINT_NEWLINE       
             87 JUMP_ABSOLUTE           66
        >>   90 POP_BLOCK           

 12     >>   91 LOAD_CONST               4 ('finished')
             94 PRINT_ITEM          
             95 PRINT_NEWLINE       
             96 LOAD_CONST               0 (None)
             99 RETURN_VALUE        
         </dis>
         <names> ('items',)</names>
         <varnames> ('a', 'm', 'n', 'args', 'kwargs', 'x', 'p', 'k', 'v')</varnames>
         <freevars> ()</freevars>
         <cellvars> ()</cellvars>
         <filename> 'test_func_param2.py'</filename>
         <name> 'foo'</name>
         <firstlineno> 1</firstlineno>
         <consts>
            None
            5
            'args:'
            'kwargs:'
            'finished'
         </consts>
         <lnotab> 0001060105010501050105010d010901050119010d01</lnotab>
      </code>
      10
      1
      3
      4
      5
      6
      'b'
      'c'
      'n'
      <code>
         <argcount> 2 </argcount>
         <nlocals> 2</nlocals>
         <stacksize> 1</stacksize>
         <flags> 0043</flags>
         <code> 7c000047487c0100474864000053</code>
         <dis>
 24           0 LOAD_FAST                0 (a)
              3 PRINT_ITEM          
              4 PRINT_NEWLINE       

 25           5 LOAD_FAST                1 (b)
              8 PRINT_ITEM          
              9 PRINT_NEWLINE       
             10 LOAD_CONST               0 (None)
             13 RETURN_VALUE        
         </dis>
         <names> ()</names>
         <varnames> ('a', 'b')</varnames>
         <freevars> ()</freevars>
         <cellvars> ()</cellvars>
         <filename> 'test_func_param2.py'</filename>
         <name> 'foo2'</name>
         <firstlineno> 23</firstlineno>
         <consts>
            None
         </consts>
         <lnotab> 00010501</lnotab>
      </code>
      <code>
         <argcount> 1 </argcount>
         <nlocals> 2</nlocals>
         <stacksize> 1</stacksize>
         <flags> 0047</flags>
         <code> 7c0000474864000053</code>
         <dis>
 31           0 LOAD_FAST                0 (a)
              3 PRINT_ITEM          
              4 PRINT_NEWLINE       
              5 LOAD_CONST               0 (None)
              8 RETURN_VALUE        
         </dis>
         <names> ()</names>
         <varnames> ('a', 'args')</varnames>
         <freevars> ()</freevars>
         <cellvars> ()</cellvars>
         <filename> 'test_func_param2.py'</filename>
         <name> 'foo3'</name>
         <firstlineno> 30</firstlineno>
         <consts>
            None
         </consts>
         <lnotab> 0001</lnotab>
      </code>
      <code>
         <argcount> 0 </argcount>
         <nlocals> 1</nlocals>
         <stacksize> 1</stacksize>
         <flags> 0047</flags>
         <code> 64000053</code>
         <dis>
 37           0 LOAD_CONST               0 (None)
              3 RETURN_VALUE        
         </dis>
         <names> ()</names>
         <varnames> ('args',)</varnames>
         <freevars> ()</freevars>
         <cellvars> ()</cellvars>
         <filename> 'test_func_param2.py'</filename>
         <name> 'foo4'</name>
         <firstlineno> 36</firstlineno>
         <consts>
            None
         </consts>
         <lnotab> 0001</lnotab>
      </code>
      <code>
         <argcount> 1 </argcount>
         <nlocals> 1</nlocals>
         <stacksize> 1</stacksize>
         <flags> 0043</flags>
         <code> 64000053</code>
         <dis>
 40           0 LOAD_CONST               0 (None)
              3 RETURN_VALUE        
         </dis>
         <names> ()</names>
         <varnames> ('a',)</varnames>
         <freevars> ()</freevars>
         <cellvars> ()</cellvars>
         <filename> 'test_func_param2.py'</filename>
         <name> 'foo5'</name>
         <firstlineno> 39</firstlineno>
         <consts>
            None
         </consts>
         <lnotab> 0001</lnotab>
      </code>
      None
   </consts>
   <lnotab> 0c0d0601250201010d0201011302090401010d02090301010a020903</lnotab>
</code>
